plex2nfo/__init__.py
plex2nfo/__main__.py
plex2nfo/cli.py
plex2nfo/updater.py
plex2nfo-1.0.4.dist-info/LICENSE
plex2nfo-1.0.4.dist-info/METADATA
plex2nfo-1.0.4.dist-info/WHEEL
plex2nfo-1.0.4.dist-info/entry_points.txt
plex2nfo-1.0.4.dist-info/RECORD
