Metadata-Version: 2.3
Name: plex2nfo
Version: 1.0.4
Summary: Write .NFO files and download poster/backdrop images from a Plex movie library.
License: CECILL-B
Author: Matthieu Gallet
Author-email: github@19pouces.net
Maintainer: Matthieu Gallet
Maintainer-email: github@19pouces.net
Requires-Python: >=3.11,<4.0
Classifier: Development Status :: 5 - Production/Stable
Classifier: License :: CeCILL-B Free Software License Agreement (CECILL-B)
Classifier: License :: OSI Approved :: CEA CNRS Inria Logiciel Libre License, version 2.1 (CeCILL-2.1)
Classifier: Operating System :: MacOS :: MacOS X
Classifier: Operating System :: POSIX :: BSD
Classifier: Operating System :: POSIX :: Linux
Classifier: Operating System :: Unix
Classifier: Programming Language :: Python :: 3
Classifier: Programming Language :: Python :: 3.11
Classifier: Programming Language :: Python :: 3.12
Classifier: Programming Language :: Python :: 3.13
Classifier: Programming Language :: Python :: 3 :: Only
Classifier: Programming Language :: Python :: 3.14
Requires-Dist: plexapi (>=4.16.1,<5.0.0)
Requires-Dist: requests (>=2.31.0,<3.0.0)
Requires-Dist: systemlogger (>=0.2.2,<0.3.0)
Requires-Dist: termcolor (>=3.0.1,<4.0.0)
Requires-Dist: tqdm (>=4.67.1,<5.0.0)
Project-URL: Documentation, https://github.com/d9pouces/plex2nfo
Project-URL: Repository, https://github.com/d9pouces/plex2nfo
